pyremotenode/__init__.py
pyremotenode/cli.py
pyremotenode/messaging.py
pyremotenode/schedule.py
pyremotenode/comms/__init__.py
pyremotenode/comms/base.py
pyremotenode/comms/connections.py
pyremotenode/comms/iridium.py
pyremotenode/comms/utils.py
pyremotenode/receiver/__init__.py
pyremotenode/receiver/certus.py
pyremotenode/tasks/__init__.py
pyremotenode/tasks/base.py
pyremotenode/tasks/commands.py
pyremotenode/tasks/iridium.py
pyremotenode/tasks/loh.py
pyremotenode/tasks/ssh.py
pyremotenode/tasks/ts7400.py
pyremotenode/utils/__init__.py
pyremotenode/utils/config.py
pyremotenode/utils/gps.py
pyremotenode/utils/system.py
pyremotenode-0.6.1.dist-info/LICENSE
pyremotenode-0.6.1.dist-info/METADATA
pyremotenode-0.6.1.dist-info/WHEEL
pyremotenode-0.6.1.dist-info/entry_points.txt
pyremotenode-0.6.1.dist-info/top_level.txt
pyremotenode-0.6.1.dist-info/RECORD
