Metadata-Version: 2.1
Name: pyremotenode
Version: 0.6.1
Summary: A service library for controlling low power devices
Home-page: http://www.github.com/antarctica/pyremotenode
Author: James Byrne
Author-email: digitalinnovation@bas.ac.uk
License: UNKNOWN
Keywords: telecommunications,scheduling
Platform: UNKNOWN
Classifier: Development Status :: 4 - Beta
Classifier: Environment :: Console
Classifier: Intended Audience :: Information Technology
Classifier: Intended Audience :: Science/Research
Classifier: Intended Audience :: Telecommunications Industry 
Classifier: License :: OSI Approved :: MIT License
Classifier: Natural Language :: English
Classifier: Operating System :: POSIX
Classifier: Programming Language :: Python :: 3
Classifier: Programming Language :: Python :: 3.5
Classifier: Programming Language :: Python :: 3.6
Classifier: Programming Language :: Python :: 3.7
Classifier: Programming Language :: Python :: 3.8
Classifier: Topic :: Communications
Classifier: Topic :: Communications :: Telephony
Classifier: Topic :: Scientific/Engineering
Classifier: Topic :: Software Development :: Embedded Systems
Requires-Python: >=3.5, <3.10
Requires-Dist: apscheduler (==3.9.1.post1)
Requires-Dist: pyserial
Requires-Dist: tzlocal
Requires-Dist: xmodem
Provides-Extra: docs
Provides-Extra: receiver
Provides-Extra: release
Requires-Dist: build (==0.5.1) ; extra == 'release'
Requires-Dist: twine (==1.15.0) ; extra == 'release'
Provides-Extra: test
Requires-Dist: pytest (<6,>3) ; extra == 'test'
